{"format":2,"version":"5.2.1","globals":"a066862f43a7a313ddd95e20c516babb","files":{"api_models_py":{"hash":"abcf73231265cb1a849f902ce086661c","index":{"nums":[1,11,0,0,0,0,0],"html_filename":"api_models_py.html","relative_filename":"api/models.py"}},"api_serializers_py":{"hash":"f352826e4406a306070e416245f7be9c","index":{"nums":[1,6,0,0,0,0,0],"html_filename":"api_serializers_py.html","relative_filename":"api/serializers.py"}},"api_views_py":{"hash":"7150a3a365f78bb757041a63b50dd0c2","index":{"nums":[1,44,0,0,0,0,0],"html_filename":"api_views_py.html","relative_filename":"api/views.py"}},"backend_settings_py":{"hash":"58e74c337507bf936d40fdb415c5311e","index":{"nums":[1,19,0,0,0,0,0],"html_filename":"backend_settings_py.html","relative_filename":"backend/settings.py"}}}}